{
 "Address": {
  "type": "string",
  "isKey": false,
  "isArray": false,
  "description": " The bridge identifier of the root of the spanning tree",
  "default": "",
  "position": 2,
  "selections": " {'pattern'",
  "queryparam": "",
  "accelerated": false,
  "min": 0,
  "max": 0,
  "len": 0
 },
 "ForceVersion": {
  "type": "int32",
  "isKey": false,
  "isArray": false,
  "description": " TODO",
  "default": "",
  "position": 7,
  "selections": "",
  "queryparam": "",
  "accelerated": false,
  "min": 0,
  "max": 0,
  "len": 0
 },
 "ForwardDelay": {
  "type": "int32",
  "isKey": false,
  "isArray": false,
  "description": " The value that all bridges use for ForwardDelay when this bridge is acting as the root.  Note that 802.1D-1998 specifies that the range for this parameter is related to the value of MaxAge.  The granularity of this timer is specified by 802.1D-1998 to be 1 second.  An agent may return a badValue error if a set is attempted to a value that is not a whole number of seconds.",
  "default": "",
  "position": 6,
  "selections": " {'range'",
  "queryparam": "",
  "accelerated": false,
  "min": 0,
  "max": 0,
  "len": 0
 },
 "HelloTime": {
  "type": "int32",
  "isKey": false,
  "isArray": false,
  "description": " The value that all bridges use for HelloTime when this bridge is acting as the root.  The granularity of this timer is specified by 802.1D-1998 to be 1 second.  An agent may return a badValue error if a set is attempted    to a value that is not a whole number of seconds.",
  "default": "",
  "position": 5,
  "selections": " {'range'",
  "queryparam": "",
  "accelerated": false,
  "min": 0,
  "max": 0,
  "len": 0
 },
 "MaxAge": {
  "type": "int32",
  "isKey": false,
  "isArray": false,
  "description": " The value that all bridges use for MaxAge when this bridge is acting as the root.  Note that 802.1D-1998 specifies that the range for this parameter is related to the value of HelloTime.  The granularity of this timer is specified by 802.1D-1998 to be 1 second.  An agent may return a badValue error if a set is attempted to a value that is not a whole number of seconds.",
  "default": "",
  "position": 4,
  "selections": " {'range'",
  "queryparam": "",
  "accelerated": false,
  "min": 0,
  "max": 0,
  "len": 0
 },
 "Priority": {
  "type": "int32",
  "isKey": false,
  "isArray": false,
  "description": " The value of the write-able portion of the Bridge ID (i.e.",
  "default": "",
  "position": 3,
  "selections": " {'range'",
  "queryparam": "",
  "accelerated": false,
  "min": 0,
  "max": 0,
  "len": 0
 },
 "TxHoldCount": {
  "type": "int32",
  "isKey": false,
  "isArray": false,
  "description": " TODO",
  "default": "",
  "position": 8,
  "selections": "",
  "queryparam": "",
  "accelerated": false,
  "min": 0,
  "max": 0,
  "len": 0
 },
 "Vlan": {
  "type": "uint16",
  "isKey": true,
  "isArray": false,
  "description": " Each bridge is associated with a domain.  Typically this domain is represented as the vlan; The default domain is typically 1",
  "default": "",
  "position": 1,
  "selections": "",
  "queryparam": "",
  "accelerated": false,
  "min": 0,
  "max": 0,
  "len": 0
 }
}